{
	"isSuccess": true,
	"data": {
		"ruleName": "海外",
		"roadName": "海外",
		"adModelName": "stumpme海外",
		"loadStrategy": {
			"maxConcurrent": 5,
			"waitingTime": 120000
		},
		"showStrategy": {
			"maxDailyShow": 999,
			"pickStrategy": {
				"name": "highestShow"
			},
			"interstitialCoolDown": 0,
			"interstitialStartupCoolDown": 0,
			"interstitialMaxDaily": 999,
			"interstitialShowTriggerTimes": 0
		},
		"adNetworkShowStrategy": {},
		"ingame": {},
		"adtypes": {
			"reward": {
				"entrysMap": {
					"default_reward": "2629"
				},
				"placementGroups": {
					"2629": {
						"placementGroupId": "2629",
						"version": 8,
						"adunits": [ 
							{
								"adunitId": "2631",
								"priority": 99,
								"placements": [
									{
										"network": "admob",
										"versin": 18,
										"content": "custom selector",
										"placementData": {
											"content-type": "text/html; charset=UTF-8",
											"x-ad-timeout-ms": 30000,
											"x-adtype": "custom",
											"x-browser-agent": 0,
											"x-custom-event-class-data": "{\"adunit\":\"ca-app-pub-9865132840946459/8726603840\",\"appid\":\"ca-app-pub-9865132840946459~9965262382\",\"isbiding\":\"false\"}",
											"x-custom-event-class-name": "com.mopub.mobileads.GooglePlayServicesRewardedVideo",
											"x-height": 640,
											"x-networktype": "admob",
											"x-refreshtime": 60,
											"x-width": 360
										},
										"placement": "ca-app-pub-9865132840946459/8726603840",
										"price": 2
									}
								]
							},
							{
								"adunitId": "2635",
								"priority": 95,
								"placements": [
									{
										"network": "unity",
										"versin": 11,
										"content": "custom selector",
										"placementData": {
											"content-type": "text/html; charset=UTF-8",
											"x-ad-timeout-ms": 30000,
											"x-adtype": "custom",
											"x-browser-agent": 0,
											"x-custom-event-class-data": "{\"gameId\":\"3354601\",\"zoneId\":\"rwd20AN\"}",
											"x-custom-event-class-name": "com.mopub.mobileads.UnityRewardedVideo",
											"x-height": 640,
											"x-networktype": "unity",
											"x-refreshtime": 60,
											"x-width": 360
										},
										"placement": "3354601-rwd20AN",
										"price": 1
									},
									{
										"network": "unity",
										"versin": 28,
										"content": "custom selector",
										"placementData": {
											"content-type": "text/html; charset=UTF-8",
											"x-ad-timeout-ms": 30000,
											"x-adtype": "custom",
											"x-browser-agent": 0,
											"x-custom-event-class-data": "{\"gameId\":\"3354601\",\"zoneId\":\"rewardedVideo\"}",
											"x-custom-event-class-name": "com.mopub.mobileads.UnityRewardedVideo",
											"x-height": 640,
											"x-networktype": "unity",
											"x-refreshtime": 60,
											"x-width": 360
										},
										"placement": "3354601-rewardedVideo",
										"price": 1
									}
								]
							}
						]
					}
				},
				"entrysForbid": []
			},
			"interstitial": {
				"entrysMap": {
					"default_interstitial": "2637"
				},
				"placementGroups": {
					"2637": {
						"placementGroupId": "2637",
						"version": 9,
						"adunits": [
							{
								"adunitId": "2638",
								"priority": 100,
								"placements": [
									{
										"network": "admob",
										"versin": 7,
										"content": "custom selector",
										"placementData": {
											"content-type": "text/html; charset=UTF-8",
											"x-ad-timeout-ms": 30000,
											"x-adtype": "custom",
											"x-browser-agent": 0,
											"x-custom-event-class-data": "{\"adUnitID\":\"ca-app-pub-9865132840946459/8783221819\",\"adHeight\":640,\"adWidth\":360,\"appid\":\"ca-app-pub-9865132840946459~9965262382\",\"isbiding\":\"false\"}",
											"x-custom-event-class-name": "com.mopub.mobileads.GooglePlayServicesInterstitial",
											"x-height": 640,
											"x-networktype": "admob",
											"x-refreshtime": 60,
											"x-width": 360
										},
										"placement": "ca-app-pub-9865132840946459/8783221819",
										"price": 8
									}
								]
							},
							{
								"adunitId": "2639",
								"priority": 99,
								"placements": [
									{
										"network": "applovin",
										"versin": 0,
										"content": "custom selector",
										"placementData": {
											"content-type": "text/html; charset=UTF-8",
											"x-ad-timeout-ms": 30000,
											"x-adtype": "custom",
											"x-browser-agent": 0,
											"x-custom-event-class-data": "{\"zone_id\":\"707544c7cb8b0b96\",\"sdk_key\":\"b9K1tDNCUHHCIznly_WVZ8JA2ruHyzpeKe2Hes5PvNd5m19_2SmcuAXMfsZoSBGnPqrWc64yS73ZnyJwmfa1-Z\"}",
											"x-custom-event-class-name": "com.mopub.mobileads.AppLovinInterstitial",
											"x-height": 640,
											"x-networktype": "applovin",
											"x-refreshtime": 60,
											"x-width": 360
										},
										"placement": "707544c7cb8b0b96",
										"price": 0.1
									},
									{
										"network": "applovin",
										"versin": 0,
										"content": "custom selector",
										"placementData": {
											"content-type": "text/html; charset=UTF-8",
											"x-ad-timeout-ms": 30000,
											"x-adtype": "custom",
											"x-browser-agent": 0,
											"x-custom-event-class-data": "{\"zone_id\":\"b032a28bb2d73d1a\",\"sdk_key\":\"b9K1tDNCUHHCIznly_WVZ8JA2ruHyzpeKe2Hes5PvNd5m19_2SmcuAXMfsZoSBGnPqrWc64yS73ZnyJwmfa1-Z\"}",
											"x-custom-event-class-name": "com.mopub.mobileads.AppLovinInterstitial",
											"x-height": 640,
											"x-networktype": "applovin",
											"x-refreshtime": 60,
											"x-width": 360
										},
										"placement": "b032a28bb2d73d1a",
										"price": 0.1
									},
									{
										"network": "applovin",
										"versin": 2,
										"content": "custom selector",
										"placementData": {
											"content-type": "text/html; charset=UTF-8",
											"x-ad-timeout-ms": 30000,
											"x-adtype": "custom",
											"x-browser-agent": 0,
											"x-custom-event-class-data": "{\"zone_id\":\"0bdafe7a49dafe2c\",\"sdk_key\":\"b9K1tDNCUHHCIznly_WVZ8JA2ruHyzpeKe2Hes5PvNd5m19_2SmcuAXMfsZoSBGnPqrWc64yS73ZnyJwmfa1-Z\"}",
											"x-custom-event-class-name": "com.mopub.mobileads.AppLovinInterstitial",
											"x-height": 640,
											"x-networktype": "applovin",
											"x-refreshtime": 60,
											"x-width": 360
										},
										"placement": "0bdafe7a49dafe2c",
										"price": 13.5
									},
									{
										"network": "applovin",
										"versin": 27,
										"content": "custom selector",
										"placementData": {
											"content-type": "text/html; charset=UTF-8",
											"x-ad-timeout-ms": 30000,
											"x-adtype": "custom",
											"x-browser-agent": 0,
											"x-custom-event-class-data": "{\"zone_id\":\"ebd12465cad448ca\",\"sdk_key\":\"b9K1tDNCUHHCIznly_WVZ8JA2ruHyzpeKe2Hes5PvNd5m19_2SmcuAXMfsZoSBGnPqrWc64yS73ZnyJwmfa1-Z\"}",
											"x-custom-event-class-name": "com.mopub.mobileads.AppLovinInterstitial",
											"x-height": 640,
											"x-networktype": "applovin",
											"x-refreshtime": 60,
											"x-width": 360
										},
										"placement": "ebd12465cad448ca",
										"price": 1
									},
									{
										"network": "applovin",
										"versin": 1,
										"content": "custom selector",
										"placementData": {
											"content-type": "text/html; charset=UTF-8",
											"x-ad-timeout-ms": 30000,
											"x-adtype": "custom",
											"x-browser-agent": 0,
											"x-custom-event-class-data": "{\"zone_id\":\"770b08b88a57e759\",\"sdk_key\":\"b9K1tDNCUHHCIznly_WVZ8JA2ruHyzpeKe2Hes5PvNd5m19_2SmcuAXMfsZoSBGnPqrWc64yS73ZnyJwmfa1-Z\"}",
											"x-custom-event-class-name": "com.mopub.mobileads.AppLovinInterstitial",
											"x-height": 640,
											"x-networktype": "applovin",
											"x-refreshtime": 60,
											"x-width": 360
										},
										"placement": "770b08b88a57e759",
										"price": 7
									}
								]
							},
							{
								"adunitId": "2642",
								"priority": 96,
								"placements": [
									{
										"network": "unity",
										"versin": 22,
										"content": "custom selector",
										"placementData": {
											"content-type": "text/html; charset=UTF-8",
											"x-ad-timeout-ms": 30000,
											"x-adtype": "custom",
											"x-browser-agent": 0,
											"x-custom-event-class-data": "{\"gameId\":\"3354601\",\"zoneId\":\"INT\"}",
											"x-custom-event-class-name": "com.mopub.mobileads.UnityInterstitial",
											"x-height": 640,
											"x-networktype": "unity",
											"x-refreshtime": 60,
											"x-width": 360
										},
										"placement": "3354601-INT",
										"price": 1
									}
								]
							}
						]
					}
				},
				"entrysForbid": []
			},
			"banner": {
				"entrysMap": {
					"default_banner": "2644"
				},
				"placementGroups": {
					"2644": {
						"placementGroupId": "2644",
						"version": 0,
						"adunits": [
							{
								"adunitId": "2645",
								"priority": 100,
								"placements": [
									{
										"network": "admob",
										"versin": 2,
										"content": "custom selector",
										"placementData": {
											"content-type": "text/html; charset=UTF-8",
											"x-ad-timeout-ms": 30000,
											"x-adtype": "custom",
											"x-browser-agent": 0,
											"x-custom-event-class-data": "{\"adUnitID\":\"ca-app-pub-9865132840946459/3071786635\",\"adHeight\":50,\"adWidth\":320,\"appid\":\"ca-app-pub-9865132840946459~9965262382\",\"isbiding\":\"false\"}",
											"x-custom-event-class-name": "com.mopub.mobileads.GooglePlayServicesBanner",
											"x-height": 50,
											"x-networktype": "admob",
											"x-refreshtime": 10,
											"x-width": 320
										},
										"placement": "ca-app-pub-9865132840946459/3071786635",
										"price": 4
									},
									{
										"network": "unity",
										"versin": 1,
										"content": "custom selector",
										"placementData": {
											"content-type": "text/html; charset=UTF-8",
											"x-ad-timeout-ms": 30000,
											"x-adtype": "custom",
											"x-browser-agent": 0,
											"x-custom-event-class-data": "{\"gameId\":\"3354601\",\"zoneId\":\"banner\"}",
											"x-custom-event-class-name": "com.mopub.mobileads.UnityBanner",
											"x-height": 50,
											"x-networktype": "unity",
											"x-refreshtime": 10,
											"x-width": 320
										},
										"placement": "3354601-banner",
										"price": 0.2
									}
								]
							}
						]
					}
				},
				"entrysForbid": []
			},
			"native": {
				"entrysMap": {
					"default_native": "2646"
				},
				"placementGroups": {
					"2646": {
						"placementGroupId": "2646",
						"version": 0,
						"adunits": [
							{
								"adunitId": "2647",
								"priority": 100,
								"placements": [
									{
										"network": "admob",
										"versin": 1,
										"content": "custom selector",
										"placementData": {
											"content-type": "text/html; charset=UTF-8",
											"x-ad-timeout-ms": 30000,
											"x-adtype": "custom",
											"x-browser-agent": 0,
											"x-custom-event-class-data": "{\"adunit\":\"ca-app-pub-9865132840946459/9853018062\",\"appid\":\"ca-app-pub-9865132840946459~9965262382\",\"isbiding\":\"false\"}",
											"x-custom-event-class-name": "com.erasuper.nativeads.GooglePlayServicesNative",
											"x-height": 640,
											"x-networktype": "admob",
											"x-refreshtime": 10,
											"x-width": 360
										},
										"placement": "ca-app-pub-9865132840946459/9853018062",
										"price": 1
									}
								]
							}
						]
					}
				},
				"entrysForbid": []
			}
		}
	}
}
